<?xml version="1.0" encoding="utf-8"?>
<Instructions>
  <DaySkipper>
    <text>System time unsynced</text>
    <text>Do NOT set current time between daylight saving (1am - 3am)</text>
    <text>Y-comm glitch activated</text>
    <text>Goto Pokemon Center to prevent crash</text>
    <text>Hover cursor on Date and Time</text>
    <text>Plug the Arduino/Teensy to the Switch</text>
  </DaySkipper>
  <DaySkipper_Unlimited>
    <text>System time unsynced</text>
    <text>Set current date to 1st of any month with 31 days</text>
    <text>Y-comm glitch activated</text>
    <text>Goto Pokemon Center to prevent crash</text>
    <text>Hover cursor on Date and Time</text>
    <text>Plug the Arduino/Teensy to the Switch</text>
  </DaySkipper_Unlimited>
  <TurboA></TurboA>
  <WattFarmer>
    <text>Set text speed to Fast</text>
    <text>Stand in front of a wishing piece den</text>
    <text>System time unsynced</text>
    <text>Y-comm glitch activated</text>
  </WattFarmer>
  <FriendDeleteAdd>
    <text>Hover cursor on the last friend</text>
    <text>Plug the Arduino/Teensy to the Switch</text>
  </FriendDeleteAdd>
  <BerryFarmer>
    <text>Set text speed to Fast</text>
    <text>Stand in front of a berry tree</text>
    <text>Stay away from wild pokemon that can run into you</text>
    <text>System time unsynced</text>
    <text>Y-comm glitch activated</text>
  </BerryFarmer>
  <AutoLoto>
    <text>Set text speed to Fast</text>
    <text>Stand in front of Rotom PC</text>
    <text>System time unsynced</text>
    <text>Y-comm glitch activated</text>
  </AutoLoto>
  <BoxRelease>
    <text>Set text speed to Fast, save game first</text>
    <text>All release boxes are adjacent to each other</text>
    <text>All release boxes don't have any eggs and completely filled</text>
    <text>Set cursor mode to "Select" (red)</text>
    <text>Move cursor to leftmost box's top left corner</text>
  </BoxRelease>
  <AutoFossil>
	<text>Set Send to Boxes to Automatic, Give Nicknames to Don't give</text>
	<text>Set Sound Effects volume to 0 (Require Hi-tech Earbuds)</text>
    <text>Set text speed to Fast, save in front of Cara Liss</text>
    <text>Fossil pokemon already registered in the Pokedex</text>
    <text>Talk to Cara Liss to check the slot for each fossil</text>
    <text>Have enough number for both fossils</text>
  </AutoFossil>
  <AutoFossil_GR>
	<text>Set Send to Boxes to Automatic, Give Nicknames to Don't give</text>
	<text>Set Sound Effects volume to 0 (Require Hi-tech Earbuds)</text>
    <text>Set text speed to Fast, save in front of Cara Liss</text>
    <text>Fossil pokemon already registered in the Pokedex</text>
    <text>Talk to Cara Liss to check the slot for each fossil</text>
    <text>Have enough number for both fossils</text>
  </AutoFossil_GR>
  <Auto3DaySkipper>
    <text>Set text speed to Fast</text>
    <text>Collect watts of a wishing piece den and save</text>
    <text>System time unsynced</text>
  </Auto3DaySkipper>
  <BoxSurpriseTrade>
    <text>Set text speed to Fast</text>
    <text>Goto any places that is not Wild Area (reduce lag)</text>
    <text>Don't stand in front of any NPCs</text>
    <text>All trade boxes are adjacent to each other</text>
    <text>All trade boxes don't have any eggs, empty spaces are fine</text>
    <text>Goto PC and scroll to the leftmost box then exit</text>
    <text>Connect to the internet</text>
  </BoxSurpriseTrade>
  <AutoHost>
    <text>Set text speed to Fast</text>
    <text>Collect watts of a wishing piece den and save</text>
    <text>Disconnet from the internet</text>
    <text>(Optional) Skipping 3 days require system time unsynced</text>
    <text>(Optional) Use wired connection for stability</text>
  </AutoHost>
  <EggCollector>
    <text>Set text speed to Fast</text>
    <text>Set Send to Box to Automatic in Options</text>
    <text>Have plenty of space in your PC</text>
    <text>Have a full party without any eggs, collected eggs will goto box</text>
    <text>Have a fully upgraded Rotom Bike (use WattFarmer)</text>
    <text>Goto Route 5 Nursery and charge up Rotom Bike turbo boost</text>
    <text>Cycle to the left side of the Nursery worker, facing North-East</text>
    <text>(Optional) Defeat GAME FREAK's Morimoto to get Oval Charm</text>
    <text>(Optional) Pokemon in Nursery have different trainer ID</text>
  </EggCollector>
  <EggCollector_IT>
    <text>Set text speed to Fast</text>
    <text>Set Send to Box to Automatic in Options</text>
    <text>Have plenty of space in your PC</text>
    <text>Have a full party without any eggs, collected eggs will goto box</text>
    <text>Have a fully upgraded Rotom Bike (use WattFarmer)</text>
    <text>Goto Route 5 Nursery and charge up Rotom Bike turbo boost</text>
    <text>Cycle to the left side of the Nursery worker, facing North-East</text>
    <text>(Optional) Defeat GAME FREAK's Morimoto to get Oval Charm</text>
    <text>(Optional) Pokemon in Nursery have different trainer ID</text>
  </EggCollector_IT>
  <EggHatcher>
    <text>Set text speed to Fast</text>
    <text>Set Give Nicknames to Don't give in Options</text>
    <text>Have only one pokemon with Flame Body in your party</text>
    <text>Have the hatching pokemon already registered in the Pokedex</text>
    <text>Have a fully upgraded Rotom Bike (use WattFarmer)</text>
    <text>Goto Route 5 Nursery and charge up Rotom Bike turbo boost</text>
    <text>From nursery, cycle south west until you hit the NPC on the bridge</text>
    <text>All columns of hatching eggs in PC must be adjacent to each other</text>
    <text>Each column must have 5 eggs, except the rightmost (last) column</text>
    <text>All eggs must be in the same egg cycle group</text>
    <text>Move the cursor to the top left of the leftmost box (first column)</text>
    <text>Press Y to change the cursor to Multiselect mode (Green)</text>
  </EggHatcher>
  <AutoBattleTower>
    <text>Set text speed to Fast and Battle Effects to Off</text>
    <text>Rent team "0000-0006-15Y4-3R" at VS Battle Stadium (Team detail in Manual)</text>
	<text>Join Single Battle on Battle Tower, wait until you can press Fight</text>
  </AutoBattleTower>
  <AutoTournament>
    <text>Set text speed to Fast and Battle Effects to Off</text>
    <text>Use ONLY Zacian and with ONLY Max PP Up Behemoth Blade (Iron Head)</text>
	<text>(Optional) Use ONLY one Pokemon from recommended list (check Manual)</text>
	<text>(Optional) Level up to 100, max IV and EV train the Pokemon you bring</text>
	<text>Stand in front of Wyndon Stadium receptionist</text>
  </AutoTournament>
  <GodEggDuplication>
    <text>Set text speed to Fast</text>
    <text>Set Send to Box to Manual in Options</text>
    <text>Have a full party without any eggs, put target Pokemon on top slot</text>
    <text>Have a fully upgraded Rotom Bike (use WattFarmer)</text>
	<text>Put god egg and a Ditto in Route 5 Nursery</text>
    <text>Charge up Rotom Bike turbo boost</text>
    <text>Cycle to the left side of the Nursery worker, facing North-East</text>
    <text>(Optional) Defeat GAME FREAK's Morimoto to get Oval Charm</text>
    <text>(Optional) Pokemon in Nursery have different trainer ID</text>
  </GodEggDuplication>
  <PurpleBeamFinder>
    <text>Set text speed to Fast</text>
    <text>Have at least one wishing piece</text>
    <text>Ride on a bike in front of an empty den (with watts collected) and save</text>
  </PurpleBeamFinder>
  <ShinyFiveRegi>
    <text>Set text speed to Fast and Battle Effects to Off</text>
    <text>First Pokemon must be able to run away from battle (or hold Smoke Bomb)</text>
    <text>Rock/Ice/Steel: Walk straight to the statue without lighting up any spots</text>
    <text>Eleki/Drago: Enter a battle with the Regi and run</text>
    <text>FAST MODE: First Pokemon MUST NOT be shiny/have a showable ability/high happiness</text>
  </ShinyFiveRegi>
  <ShinySwordTrio>
    <text>Set text speed to Fast and Battle Effects to Off</text>
    <text>First Pokemon must be able to run away from battle (or hold Smoke Bomb)</text>
    <text>Run into the trio Pokemon and run</text>
    <text>Stand on the spot where the trio spawns (Slow/Fast mode only: start camping)</text>
    <text>FAST MODE: First Pokemon MUST NOT be shiny/have a showable ability</text>
	<text>FAST MODE: ALL Pokemon in the team MUST NOT have high happiness</text>
	<text>FAST MODE: Weather must be CLEAR, not Sunny, Snowing, Raining etc.</text>
	<text>SHINY AWARE MODE: No following Pokemon, avatar facing up</text>
  </ShinySwordTrio>
  <DailyHighlightFarmer>
    <text>Set text speed to Fast</text>
    <text>Stand in front of Watt Trader at Snowslide Slope</text>
    <text>System time unsynced</text>
    <text>Y-comm glitch activated</text>
  </DailyHighlightFarmer>
  <ShinyRegigigas>
    <text>Set text speed to Fast and Battle Effects to Off</text>
    <text>Bring all 5 Regis with you in your team</text>
    <text>Stand in front of Regigigas den in Giant's Bed and save</text>
    <text>SOFT RESET MODE: No extra requirement</text>
	<text>SHINY AWARE MODE: First Pokemon has Reversal to OHKO Regigigas (check Manual)</text>
	<text>SHINY AWARE MODE: Reversal move of first Pokemon must have at least 10 PP</text>
	<text>SHINY AWARE MODE: Navigate to beg and hover to Leppa Berry then leave</text>
	<text>SHINY AWARE MODE: Win the raid manually at least once before starting</text>
  </ShinyRegigigas>
  <BDSP_ResetDialgaPalkia>
    <text>Set text speed to Fast and Battle Effects to Off</text>
    <text>Save in front of Dialga/Palkia</text>
  </BDSP_ResetDialgaPalkia>
  <BDSP_ResetStarter>
    <text>Set text speed to Fast and Battle Effects to Off</text>
    <text>Save just before entering Lake Verity</text>
  </BDSP_ResetStarter>
  <BDSP_MenuGlitch113>
    <text>Set text speed to Fast</text>
    <text>Go to HM list in Poketch, move cursor to Fly and minimize</text>
    <text>Go to Route 211 to the left of Celestic Town</text>
    <text>Stand to the left of the pushable boulder</text>
  </BDSP_MenuGlitch113>
  <BDSP_BoxDuplication>
    <text>Set text speed to Fast</text>
    <text>Activate Menu Glitch</text>
    <text>Go to the box you want to duplicate</text>
    <text>Make sure there's a Pokemon or Egg at the top left</text>
    <text>Make sure boxes to the right are empty</text>
  </BDSP_BoxDuplication>
  <BDSP_BoxOperation>
    <text>Set text speed to Fast</text>
    <text>(Duplicate Item only) Activate Menu Glitch</text>
    <text>Make sure all boxes are full of Pokemon (30)</text>
    <text>Go to the first (leftmost) box</text>
  </BDSP_BoxOperation>
  <BDSP_ResetLegendary>
    <text>Set text speed to Fast and Battle Effects to Off</text>
    <text>Save in front of the Legendary</text>
  </BDSP_ResetLegendary>
  <BDSP_ResetShaymin>
    <text>Set text speed to Fast and Battle Effects to Off</text>
    <text>Use D-Pad to move in front of Shaymin</text>
    <text>Have only Bike registered, have it set on fast mode</text>
    <text>First Pokemon MUST have max happiness and no popup ability</text>
    <text>Save the game</text>
  </BDSP_ResetShaymin>
  <PLA_ResetAlphaGallade>
    <text>Turn off Autosave</text>
    <text>Head back to Jubilife Village to reset RNG seeds</text>
    <text>Go to the roof of the bottom entrance of Snowpoint Temple</text>
    <text>Get on Braviary, use Y,Plus,A to gain height to get to top entrance</text>
    <text>Save in front of the top entrance</text>
  </PLA_ResetAlphaGallade>
  <PLA_ResetAlphaCrobat>
    <text>Turn off Autosave</text>
    <text>Head back to Jubilife Village to reset RNG seeds</text>
    <text>Go to the north entrance of Wayward Cave</text>
    <text>Save in front of the entrance</text>
  </PLA_ResetAlphaCrobat>
  <SV_ItemDuplication>
    <text>Turn off Autosave</text>
    <text>Go to somewhere indoors (your house)</text>
    <text>Put cloned Koraidon/Miraidon to 2nd slot of the team</text>
    <text>Add item to clone to Koraidon/Miraidon</text>
    <text>Save game, move cursor to 2nd slot pokemon</text>
  </SV_ItemDuplication>
  <SV_EggCollector>
    <text>Turn off Autosave, Text Speed to Fast</text>
    <text>Have only 2 pokemon to breed in your team</text>
    <text>Save game and start a picnic on a flat surface</text>
    <text>Move to on top of egg basket, facing picnic table and reset camera</text>
    <text>Find the location of Great PenutButter Sandwich (top left is 0,0)</text>
    <text>Exit sandwich menu</text>
  </SV_EggCollector>
  <SV_EggHatcher>
    <text>Turn off Autosave, Text Speed to Fast, Turn off Give Nicknames</text>
    <text>Have only a Flame Body pokemon in your party with an attacking move</text>
    <text>Have the hatching pokemon already registered in the Pokedex</text>
    <text>Go to the top of Poco Path lighthouse</text>
    <text>Get on ride pokemon, hold right to move along the edge for one loop</text>
    <text>Save game, go to Boxes, sort eggs column by column from left to right</text>
    <text>All eggs must be in the same egg cycle group</text>
    <text>Move the cursor to the top left of the leftmost box (first column)</text>
  </SV_EggHatcher>
  <SV_BoxRelease>
    <text>Turn off Autosave, Text Speed to Fast</text>
    <text>Go to Boxes, sort pokemon from left to right, top to bottom</text>
    <text>Move cursor to the top left pokemon, save game</text>
  </SV_BoxRelease>
  <SV_GimmighoulFarmer>
    <text>System time unsynced</text>
    <text>Turn off Autosave, Text Speed to Fast</text>
    <text>Stand in front of a Gimmighoul in a Pokemon Center</text>
    <text>Talk to it to get its coin and save game</text>
  </SV_GimmighoulFarmer>
</Instructions>
